{
    "menu": [
        {
            "name": "Sessions",
            "title": "Sessions",
            "view": "sessionsAndDetail",
            "css": "scheduleButton menu-list-item-background"
        },
        {
            "name": "Attendees",
            "title": "Attendees",
            "view": "attendees",
            "css": "attendeesButton menu-list-item-background"
        },
        {
            "name": "Exhibitors",
            "title": "Exhibitors",
            "view": "exhibitorAndDetail",
            "css": "exhibitorsButton menu-list-item-background"
        },
        {
            "name": "Map",
            "title": "Map",
            "view": "mapevent",
            "css": "mapButton menu-list-item-background"
        },
        {
            "name": "Materials",
            "title": "Materials",
            "view": "materialPanel",
            "css": "materialButton menu-list-item-background"
        },
        {
            "name": "Notes",
            "title": "Notes",
            "view": "notepanel",
            "css": "notesButton menu-list-item-background"
        },
        {
            "name": "Presenters",
            "title": "Presenters",
            "view": "presenterpanel",
            "css": "presenterButton menu-list-item-background"
        },
        {
            "name": "Event Description",
            "title": "Event Description",
            "view": "descriptioneventpanel",
            "css": "descriptionButton menu-list-item-background"
        },
        {
            "name": "Badge",
            "title": "Badge",
            "view": "badgepanel",
            "css": "badgeButton menu-list-item-background"
        }
    ]
}
